{ "ExplosionInfo" : {
    "type" : { "type": "ExplosionType" },
    "damage_type" : { "type": "DamageInfoType", "default": "DamageInfoType_None" },
    "inner_radius" : { "type": "float", "default": 0 },
    "outer_radius" : { "type": "float", "default": 0 },
    "stagger_radius" : { "type": "float", "default": 0 },
    "cone_angle" : { "type": "float", "default": 0 },
    "camera_shake_radius" : { "type": "float", "default": 0 },
    "shake_assets" : { "type": "array", "subtype": "ulong", "description": "[camera_shake]" },
    "particle_effect_path" : { "type": "ulong", "description": "[particles]" },
    "audio_event" : { "type": "uint" },
    "crater_type" : { "type": "TerrainDeformationType" },
    "surface_impact_type" : { "type": "SurfaceImpactType", "default": "SurfaceImpactType_None" },
    "hit_effect_damage_type" : { "type": "HitEffectDamageType", "default": "HitEffectDamageType_None" },
    "num_shrapnel_projectiles" : { "type": "uint" },
    "shrapnel_projectile_type" : { "type": "ProjectileType", "default": "ProjectileType_None" },
    "noise_template" : { "type": "NoiseTemplate", "default": "NoiseTemplate_None" },
    "wind_effect_template" : { "type": "WindEffectTemplate", "default": "WindEffectTemplate_None" },
    "fire_template" : { "type": "FireTemplate", "default": "FireTemplate_None" },
    "persistent_status_volume" : { "type": "StatusEffectTemplateType", "default": "StatusEffectTemplateType_None" },
    "status_volume_effect_time" : { "type": "float", "default": 0 },
    "status_volume_effect_audio_play" : { "type": "uint" },
    "status_volume_effect_audio_stop" : { "type": "uint" },
    "do_knockback" : { "type": "byte" },
    "disable_default_surface_impact" : { "type": "byte" },
    "is_huge_explosion" : { "type": "byte" },
    "look_for_audio_source_hijack" : { "type": "byte" }
}}
