{
  "204075488202026058": {
    "investigate_time": 20
  },
  "5102465671637479928": {
    "investigate_time": 20
  },
  "2374182306803456737": {
    "investigate_time": 20
  },
  "4355611497043427857": {
    "investigate_time": 20
  },
  "9360053548772838040": {
    "investigate_time": 20
  },
  "368460834513215015": {
    "investigate_time": 20
  },
  "8089720719317653430": {
    "investigate_time": 20
  },
  "17664573392975623128": {
    "investigate_time": 20
  },
  "1992162250168776749": {
    "investigate_time": 20
  },
  "16210383499747977185": {
    "investigate_time": 20
  },
  "6261276598951891725": {
    "investigate_time": 20
  }
}